{
  "parent": "minecraft:recipes/root",
  "rewards": {
    "recipes": [
      "eternalcore:blasting_smelt_impure_iron_dust"
    ]
  },
  "criteria": {
    "has_impure_iron_dust": {
      "trigger": "minecraft:inventory_changed",
      "conditions": {
        "items": [
          {
            "tag": "forge:impure_dusts/iron"
          }
        ]
      }
    },
    "has_the_recipe": {
      "trigger": "minecraft:recipe_unlocked",
      "conditions": {
        "recipe": "eternalcore:blasting_smelt_impure_iron_dust"
      }
    }
  },
  "requirements": [
    [
      "has_impure_iron_dust",
      "has_the_recipe"
    ]
  ]
}